CionAttack/CionAttack.py
CionAttack/GuiTest1.py
CionAttack/GuiTest2_Coin_Flip.py
CionAttack/Tree.py
Cion_Attack/Cion_Attack.py
Cion_Attack/GuiTest1.py
Cion_Attack/GuiTest2_Coin_Flip.py
Cion_Attack/Tree.py
Roulette_Attack/GuiTest1.py
Roulette_Attack/GuiTest2_Coin_Flip.py
Roulette_Attack/Roulette_Attack.py
Roulette_Attack/Tree.py
attack_cion/GuiTest1.py
attack_cion/GuiTest2_Coin_Flip.py
attack_cion/Tree.py
CionAttack-0.1.3.dist-info/METADATA
CionAttack-0.1.3.dist-info/WHEEL
CionAttack-0.1.3.dist-info/top_level.txt
CionAttack-0.1.3.dist-info/RECORD
