Metadata-Version: 2.1
Name: CionAttack
Version: 0.1.3
Summary: A
Home-page: UNKNOWN
Author: io_O
Author-email: fastorder9@gmail.com
License: MIT
Platform: UNKNOWN
Classifier: License :: OSI Approved :: MIT License
Classifier: Programming Language :: Python :: 2
Classifier: Programming Language :: Python :: 3
